Metadata-Version: 1.1
Name: appveyordist
Version: 1.0.0
Summary: Download appveyor build artefacts to project dist
Home-page: https://github.com/mcfletch/appveyordist
Author: Mike C. Fletcher
Author-email: mcfletch@vrplumber.com
License: MIT
Platform: UNKNOWN
Classifier: License :: OSI Approved :: MIT License
Classifier: Programming Language :: Python
Classifier: Programming Language :: Python :: 3
Classifier: Programming Language :: Python :: 3.6
Classifier: Programming Language :: Python :: 3.7
